intake_stac/__init__.py
intake_stac/catalog.py
intake_stac-0.4.0.dist-info/LICENSE
intake_stac-0.4.0.dist-info/METADATA
intake_stac-0.4.0.dist-info/WHEEL
intake_stac-0.4.0.dist-info/entry_points.txt
intake_stac-0.4.0.dist-info/top_level.txt
intake_stac-0.4.0.dist-info/RECORD
