Metadata-Version: 2.1
Name: intake-stac
Version: 0.4.0
Summary: An intake adapter for building intake catalogs begining with SpatioTemporal Asset Catalogs (STAC)
Home-page: https://github.com/pangeo-data/intake-stac
Maintainer: Joe Hamman
Maintainer-email: jhamman@ucar.edu
License: BSD 2-Clause
Keywords: intake stac
Platform: UNKNOWN
Requires-Python: >=3.8
License-File: LICENSE
Requires-Dist: fsspec (>=0.8.4)
Requires-Dist: intake (>=0.5.1)
Requires-Dist: intake-xarray (>=0.4)
Requires-Dist: pystac (>=1.0.0)
